MANIFEST.in
README.rst
setup.py
paano/__init__.py
paano/config.py
paano/constants.py
paano/extensions.py
paano/forms.py
paano/helpers.py
paano/models.py
paano/views.py
paano/wsgi.py
paano.egg-info/PKG-INFO
paano.egg-info/SOURCES.txt
paano.egg-info/dependency_links.txt
paano.egg-info/not-zip-safe
paano.egg-info/requires.txt
paano.egg-info/top_level.txt
paano/static/css/normalize.css
paano/static/css/styles.css
paano/static/js/jquery.filedrop.js
paano/static/js/jquery.min.js
paano/static/js/paano.js
paano/templates/paano/base.html
paano/templates/paano/category.html
paano/templates/paano/category_form.html
paano/templates/paano/index.html
paano/templates/paano/new_category.html
paano/templates/paano/new_question.html
paano/templates/paano/question.html
paano/templates/paano/question_form.html