Metadata-Version: 1.0
Name: paano
Version: 0.1.10
Summary: Dead simple FAQ/HowTo CMS
Home-page: http://github.com/marksteve/paano
Author: Mark Steve Samson
Author-email: marksteve@insynchq.com
License: MIT
Platform: any
Classifier: Development Status :: 3 - Alpha
Classifier: Environment :: Web Environment
Classifier: Intended Audience :: Developers
Classifier: License :: OSI Approved :: MIT License
Classifier: Operating System :: OS Independent
Classifier: Programming Language :: Python :: 2.6
Classifier: Programming Language :: Python :: 2.7
Classifier: Topic :: Internet :: WWW/HTTP :: Dynamic Content
Classifier: Topic :: Internet :: WWW/HTTP :: WSGI :: Application
